{"BC":"拓","CZ":"正","BG":"奈","B6":"蒼","BU":"聖","B1":"野","DJ":"後","AH":"晄","B0":"青","C6":"隼","C7":"安","A6":"前","C0":"輔","BQ":"櫻","DS":"藤","AJ":"田","DF":"遠","DQ":"遥","BM":"女","BF":"力","B5":"衣","DM":"美","AX":"瞳","B7":"恒","CA":"下","DN":"基","A8":"尾","AO":"伊","B3":"嘉","D9":"梨","AT":"一","BZ":"羽","CI":"佐","DR":"茉","A1":"塚","AR":"川","CD":"也","D3":"翔","C9":"井","DD":"木","CG":"西","AE":"音","B8":"大","02":"花","D5":"輝","CV":"龍","AL":"凪","DV":"榎","DP":"玲","AI":"永","DH":"酒","04":"空","CM":"素","A4":"羅","AF":"小","AW":"生","BW":"本","DA":"来","C2":"晃","A7":"右","A3":"理","CO":"愛","BH":"斗","BK":"陽","BS":"ン","DW":"崎","B2":"菜","DC":"心","CX":"太","DY":"胡","DZ":"久","AU":"加","CW":"世","BA":"松","C1":"セ","CL":"河","DO":"口","AM":"郎","BL":"侑","CN":"岡","CY":"武","CP":"丹","CR":"キ","BO":"平","EB":"ユ","D4":"染","D8":"樹","BE":"司","D1":"納","BP":"夢","CH":"牧","AA":"英","DK":"岩","AC":"月","BY":"白","EA":"煌","A0":"ケ","BN":"望","EC":"伸","DL":"村","CF":"寿","C5":"溝","DI":"敬","D7":"米","DG":"森","A2":"恵","AB":"瀬","B4":"虎","DT":"百","BV":"史","AQ":"深","CQ":"那","CC":"魁","DX":"粋","AY":"横","BD":"京","CJ":"陸","CE":"髙","C4":"澤","AG":"ヒ","CB":"都","AP":"橋","CU":"ロ","CS":"ジ","AZ":"光","DB":"華","00":"山","CT":"原","AK":"ホ","DE":"希","BJ":"奏","AD":"帆","D0":"高","C8":"杉","C3":"裕","D6":"優","BR":"飛","B9":"所","CK":"合","A9":"渓","AV":"沙","D2":"流","AN":"牛","BI":"堀","AS":"ゾ","A5":"ョ","BX":"雫","DU":"和","BT":"涼","BB":"内"}